{
  "timestamp": "2026-04-03T21:00:10.126674+00:00",
  "summary": {
    "threat_level": "CRITICAL",
    "primary_risk": "Stocks Bounce Back From Early Losses",
    "secondary_risk": "Brent oil spot price for actual cargo soars to $141, highest level since 2008 financial crisis",
    "market_impact": "Elevated",
    "last_updated": "2026-04-03T21:00:10.126677+00:00",
    "data_source": "NewsAPI (Live)"
  },
  "key_events": [
    {
      "event": "Stocks Bounce Back From Early Losses",
      "source": "NewsAPI",
      "impact": "See details in full report"
    },
    {
      "event": "Brent oil spot price for actual cargo soars to $141, highest level since 2008 financial crisis",
      "source": "NewsAPI",
      "impact": "See details in full report"
    },
    {
      "event": "US Burned 14 Years of Missiles in 30 Days",
      "source": "NewsAPI",
      "impact": "See details in full report"
    },
    {
      "event": "Trump\u2019s Updated 'Special Book': More Attacks on Digital, Climate, and Health Policies | Common Dreams",
      "source": "NewsAPI",
      "impact": "See details in full report"
    }
  ],
  "recent_articles": [
    {
      "title": "\u201cIt\u2019s a New World. It\u2019s the Same Constitution.\u201d",
      "source": "Slate Magazine",
      "category": "Oil & Energy"
    },
    {
      "title": "Stocks Bounce Back From Early Losses",
      "source": "Newser",
      "category": "Oil & Energy"
    },
    {
      "title": "Brent oil spot price for actual cargo soars to $141, highest level since 2008 financial crisis",
      "source": "CNBC",
      "category": "Oil & Energy"
    },
    {
      "title": "High Gas Prices? No Worries, Just Use More Ethanol",
      "source": "CleanTechnica",
      "category": "Oil & Energy"
    },
    {
      "title": "US Burned 14 Years of Missiles in 30 Days",
      "source": "Trendytechtribe.com",
      "category": "Oil & Energy"
    }
  ],
  "trading_implications": {
    "oil_volatility": "High",
    "position_sizing": "Reduce to 50%",
    "recommendation": "Cautious trading"
  }
}